odoo/addons/somconnexio/.gitignore
odoo/addons/somconnexio/CHANGELOG.md
odoo/addons/somconnexio/README.md
odoo/addons/somconnexio/__init__.py
odoo/addons/somconnexio/__manifest__.py
odoo/addons/somconnexio/diario_migracion.md
odoo/addons/somconnexio/hooks.py
odoo/addons/somconnexio/requirements.txt
odoo/addons/somconnexio/crons/contract_compute_current_tariff_cron.xml
odoo/addons/somconnexio/data/account.account.template-sc.csv
odoo/addons/somconnexio/data/account_chart_template_data.xml
odoo/addons/somconnexio/data/account_group.xml
odoo/addons/somconnexio/data/account_journal.xml
odoo/addons/somconnexio/data/account_payment_mode.xml
odoo/addons/somconnexio/data/account_tax.xml
odoo/addons/somconnexio/data/account_tax_group.xml
odoo/addons/somconnexio/data/analytic_account.xml
odoo/addons/somconnexio/data/base_automation.xml
odoo/addons/somconnexio/data/company.xml
odoo/addons/somconnexio/data/contract_terminate_reason.xml
odoo/addons/somconnexio/data/contract_terminate_user_reason.xml
odoo/addons/somconnexio/data/crm_stage_data.xml
odoo/addons/somconnexio/data/crm_team.xml
odoo/addons/somconnexio/data/fiber_signal_type_data.xml
odoo/addons/somconnexio/data/ir_config_pararameter.xml
odoo/addons/somconnexio/data/ir_sequence.xml
odoo/addons/somconnexio/data/mail_activity_type.xml
odoo/addons/somconnexio/data/mis_report.xml
odoo/addons/somconnexio/data/partner_action_tag_data.xml
odoo/addons/somconnexio/data/partner_priority.xml
odoo/addons/somconnexio/data/previous_provider_data.xml
odoo/addons/somconnexio/data/product_attribute.xml
odoo/addons/somconnexio/data/product_attribute_value.xml
odoo/addons/somconnexio/data/product_categories.xml
odoo/addons/somconnexio/data/product_category_technology_supplier_data.xml
odoo/addons/somconnexio/data/product_pack_line.xml
odoo/addons/somconnexio/data/product_product.xml
odoo/addons/somconnexio/data/product_template_attribute_line_data.xml
odoo/addons/somconnexio/data/product_template_data.xml
odoo_addon_somconnexio-16.0.1.0.13.dist-info/METADATA
odoo_addon_somconnexio-16.0.1.0.13.dist-info/WHEEL
odoo_addon_somconnexio-16.0.1.0.13.dist-info/top_level.txt
odoo_addon_somconnexio-16.0.1.0.13.dist-info/RECORD
