Metadata-Version: 2.1
Name: odoo-addon-somconnexio
Version: 16.0.1.0.13
Summary: Odoo Som Connexió customizations
Home-page: https://coopdevs.org
Author: Coopdevs Treball SCCL, Som Connexió SCCL
License: AGPL-3
Platform: UNKNOWN
Classifier: Programming Language :: Python
Classifier: Framework :: Odoo
Classifier: Framework :: Odoo :: 16.0
Classifier: License :: OSI Approved :: GNU Affero General Public License v3
Requires-Python: >=3.10
Requires-Dist: factory-boy
Requires-Dist: faker ==9.3.1
Requires-Dist: mm-proxy-python-client ==0.1.0
Requires-Dist: odoo-addon-account-asset-management <16.1dev,>=16.0dev
Requires-Dist: odoo-addon-account-banking-sepa-credit-transfer <16.1dev,>=16.0dev
Requires-Dist: odoo-addon-account-banking-sepa-direct-debit <16.1dev,>=16.0dev
Requires-Dist: odoo-addon-account-chart-update <16.1dev,>=16.0dev
Requires-Dist: odoo-addon-account-due-list <16.1dev,>=16.0dev
Requires-Dist: odoo-addon-account-financial-report <16.1dev,>=16.0dev
Requires-Dist: odoo-addon-account-payment-mode <16.1dev,>=16.0dev
Requires-Dist: odoo-addon-account-payment-order <16.1dev,>=16.0dev
Requires-Dist: odoo-addon-account-payment-partner <16.1dev,>=16.0dev
Requires-Dist: odoo-addon-account-payment-return <16.1dev,>=16.0dev
Requires-Dist: odoo-addon-account-payment-return-import <16.1dev,>=16.0dev
Requires-Dist: odoo-addon-account-payment-return-import-iso20022 <16.1dev,>=16.0dev
Requires-Dist: odoo-addon-auth-oidc <16.1dev,>=16.0dev
Requires-Dist: odoo-addon-base-import-async <16.1dev,>=16.0dev
Requires-Dist: odoo-addon-base-rest-somconnexio <16.1dev,>=16.0dev
Requires-Dist: odoo-addon-component-event <16.1dev,>=16.0dev
Requires-Dist: odoo-addon-contract <16.1dev,>=16.0dev
Requires-Dist: odoo-addon-contract-mandate <16.1dev,>=16.0dev
Requires-Dist: odoo-addon-contract-payment-mode <16.1dev,>=16.0dev
Requires-Dist: odoo-addon-crm-lead-product <16.1dev,>=16.0dev
Requires-Dist: odoo-addon-disable-login <16.1dev,>=16.0dev
Requires-Dist: odoo-addon-l10n-es-account-asset <16.1dev,>=16.0dev
Requires-Dist: odoo-addon-l10n-es-account-statement-import-n43 <16.1dev,>=16.0dev
Requires-Dist: odoo-addon-l10n-es-aeat <16.1dev,>=16.0dev
Requires-Dist: odoo-addon-l10n-es-aeat-mod111 <16.1dev,>=16.0dev
Requires-Dist: odoo-addon-l10n-es-aeat-mod190 <16.1dev,>=16.0dev
Requires-Dist: odoo-addon-l10n-es-aeat-mod303 <16.1dev,>=16.0dev
Requires-Dist: odoo-addon-l10n-es-aeat-mod347 <16.1dev,>=16.0dev
Requires-Dist: odoo-addon-l10n-es-aeat-mod349 <16.1dev,>=16.0dev
Requires-Dist: odoo-addon-l10n-es-aeat-mod390 <16.1dev,>=16.0dev
Requires-Dist: odoo-addon-l10n-es-igic <16.1dev,>=16.0dev
Requires-Dist: odoo-addon-l10n-es-mis-report <16.1dev,>=16.0dev
Requires-Dist: odoo-addon-l10n-es-partner <16.1dev,>=16.0dev
Requires-Dist: odoo-addon-l10n-es-toponyms <16.1dev,>=16.0dev
Requires-Dist: odoo-addon-mail-activity-board <16.1dev,>=16.0dev
Requires-Dist: odoo-addon-mail-activity-done <16.1dev,>=16.0dev
Requires-Dist: odoo-addon-mis-builder <16.1dev,>=16.0dev
Requires-Dist: odoo-addon-mis-builder-budget <16.1dev,>=16.0dev
Requires-Dist: odoo-addon-partner-firstname <16.1dev,>=16.0dev
Requires-Dist: odoo-addon-partner-manual-rank <16.1dev,>=16.0dev
Requires-Dist: odoo-addon-partner-priority <16.1dev,>=16.0dev
Requires-Dist: odoo-addon-product-pack <16.1dev,>=16.0dev
Requires-Dist: odoo-addon-queue-job <16.1dev,>=16.0dev
Requires-Dist: odoo-addon-server-environment <16.1dev,>=16.0dev
Requires-Dist: odoo-addon-web-chatter-position <16.1dev,>=16.0dev
Requires-Dist: odoo-addon-web-m2x-options <16.1dev,>=16.0dev
Requires-Dist: odoo-addon-web-no-bubble <16.1dev,>=16.0dev
Requires-Dist: odoo-addon-web-responsive <16.1dev,>=16.0dev
Requires-Dist: odoo-addon-web-widget-open-tab <16.1dev,>=16.0dev
Requires-Dist: odoo <16.1dev,>=16.0a
Requires-Dist: python-stdnum ==1.14
